{
  "mandala": 6,
  "sukta": 72,
  "verses": [
    {
      "id": "6.72.1",
      "mandala": 6,
      "sukta": 72,
      "rik": 1,
      "padas": [
        {
          "text": "इन्द्रा᳚सोमा॒ महि॒ तद्वां᳚ महि॒त्वं यु॒वं म॒हानि᳚ प्रथ॒मानि᳚ चक्रथुः ।",
          "begin": 0.0,
          "end": 10.617
        },
        {
          "text": "यु॒वं सूर्यं᳚ विवि॒दथु᳚र्यु॒वं स्व१॒᳚र्विश्वा॒ तमां᳚स्यहतं नि॒दश्च᳚ ॥",
          "begin": 10.617,
          "end": 19.6
        }
      ]
    },
    {
      "id": "6.72.2",
      "mandala": 6,
      "sukta": 72,
      "rik": 2,
      "padas": [
        {
          "text": "इन्द्रा᳚सोमा वा॒सय᳚थ उ॒षास॒मुत्सूर्यं᳚ नयथो॒ ज्योति᳚षा स॒ह ।",
          "begin": 0.0,
          "end": 7.256
        },
        {
          "text": "उप॒ द्यां स्क॒म्भथु॒ः स्कम्भ᳚ने॒नाप्र᳚थतं पृथि॒वीं मा॒तरं॒ वि ॥",
          "begin": 7.256,
          "end": 16.0
        }
      ]
    },
    {
      "id": "6.72.3",
      "mandala": 6,
      "sukta": 72,
      "rik": 3,
      "padas": [
        {
          "text": "इन्द्रा᳚सोमा॒वहि᳚म॒पः प᳚रि॒ष्ठां ह॒थो वृ॒त्रमनु᳚ वां॒ द्यौर᳚मन्यत ।",
          "begin": 0.0,
          "end": 9.241
        },
        {
          "text": "प्रार्णां᳚स्यैरयतं न॒दीना॒मा स᳚मु॒द्राणि᳚ पप्रथुः पु॒रूणि᳚ ॥",
          "begin": 9.241,
          "end": 16.24
        }
      ]
    },
    {
      "id": "6.72.4",
      "mandala": 6,
      "sukta": 72,
      "rik": 4,
      "padas": [
        {
          "text": "इन्द्रा᳚सोमा प॒क्वमा॒मास्व॒न्तर्नि गवा॒मिद्द᳚धथुर्व॒क्षणा᳚सु ।",
          "begin": 0.0,
          "end": 10.18
        },
        {
          "text": "ज॒गृ॒भथु॒रन᳚पिनद्धमासु॒ रुश᳚च्चि॒त्रासु॒ जग᳚तीष्व॒न्तः ॥",
          "begin": 10.18,
          "end": 15.84
        }
      ]
    },
    {
      "id": "6.72.5",
      "mandala": 6,
      "sukta": 72,
      "rik": 5,
      "padas": [
        {
          "text": "इन्द्रा᳚सोमा यु॒वम॒ङ्ग तरु᳚त्रमपत्य॒साचं॒ श्रुत्यं᳚ रराथे ।",
          "begin": 0.0,
          "end": 9.038
        },
        {
          "text": "यु॒वं शुष्मं॒ नर्यं᳚ चर्ष॒णिभ्य॒ः सं वि᳚व्यथुः पृतना॒षाह᳚मुग्रा ॥",
          "begin": 9.038,
          "end": 18.04
        }
      ]
    }
  ]
}